{ "id": "proposals-from-his-royal-highness-fon-fomuki-during-the-gudeca-agm-at-mutegene-2016", "type": "Update", "joomlaId": 28, "title": "Proposals from His Royal Highness Fon Fomuki during the GUDECA AGM at Mutegene, 2016", "slug": "proposals-from-his-royal-highness-fon-fomuki-during-the-gudeca-agm-at-mutegene-2016", "publishedAt": "2016-10-13T12:25:47.000Z", "excerpt": "1. Revision of the annual development levy - 20 000 frs for men out of home - 10 000frs for women out of home - 2 000 frs for men at home + labor - 1 000frs for women at home + labor - Guneku elements…", "body": "<p><img src=\"images/chief.jpg\" alt=\"\"></p><p>1.&nbsp;&nbsp; &nbsp;Revision of the annual development levy<br>-&nbsp;&nbsp; &nbsp;20 000 frs for men out of home<br>-&nbsp;&nbsp; &nbsp;10 000frs for women out of home<br>-&nbsp;&nbsp; &nbsp;2 000 frs for men at home + labor<br>-&nbsp;&nbsp; &nbsp;1 000frs for women at home + labor <br>-&nbsp;&nbsp; &nbsp;Guneku elements in the diaspora are encouraged to give more<br>Deadline to receive contributions is September 30th, every year<br>A circular letter should be sent to all GUDECA branch presidents informing them of the changes and let them collect the funds and channel them to the multi-purpose project.<br>NB. Living in Mbengwi is not considered home.<br>2.&nbsp;&nbsp; &nbsp;Creation of a daily market at Windig or use the existing Ngong market for a daily market. This will ease the sales of farm produce.<br>3.&nbsp;&nbsp; &nbsp;Setting aside a day of the week for a cleanup campaign where each household will clean its surroundings.<br>4.&nbsp;&nbsp; &nbsp;Revise fines for caught straying animals ( pigs, goats, sheep etc).</p>", "featuredImage": null, "images": [], "youtubeEmbeds": []
}